ask_question/__init__.py
ask_question/__main__.py
ask_question/ask_question.py
ask_question/ask_question_tui.py
ask_question-1.2.12.dist-info/licenses/LICENSE
ask_question-1.2.12.dist-info/METADATA
ask_question-1.2.12.dist-info/WHEEL
ask_question-1.2.12.dist-info/top_level.txt
ask_question-1.2.12.dist-info/RECORD
