Metadata-Version: 2.4
Name: ask_question
Version: 1.2.12
Summary: A module that simplifies the boiling process when asking the user a question via a TTY interface. (A TUI version is being developed, to call it, just add TUI at the end of the class name)
Author-email: Henry Letellier <henrysoftwarehouse@protonmail.com>
Maintainer-email: Henry Letellier <henrysoftwarehouse@protonmail.com>
License-Expression: MIT
Project-URL: Homepage, https://github.com/Hanra-s-work/ask_question
Project-URL: Documentation, https://github.com/Hanra-s-work/ask_question/blob/main/README.md
Project-URL: Repository, https://github.com/Hanra-s-work/ask_question.git
Project-URL: Issues, https://github.com/Hanra-s-work/ask_question/issues
Keywords: tty,tui,cli,survey,python,prompt,question,user input,automation,interactive,asciimatics
Classifier: Environment :: Console
Classifier: Natural Language :: English
Classifier: Development Status :: 3 - Alpha
Classifier: Operating System :: OS Independent
Classifier: Programming Language :: Python :: 3
Classifier: Programming Language :: Python :: 3.8
Classifier: Programming Language :: Python :: 3.9
Classifier: Programming Language :: Python :: 3.10
Classifier: Programming Language :: Python :: 3.11
Classifier: Programming Language :: Python :: 3.12
Classifier: Programming Language :: Python :: 3.13
Requires-Python: >=3.8
License-File: LICENSE
Provides-Extra: tui
Requires-Dist: asciimatics-overlay-ov==1.0.10; extra == "tui"
Dynamic: license-file
